test_api_sar/__init__.py
test_api_sar/test_api_sar.py
test_api_sar-0.4.0.dist-info/METADATA
test_api_sar-0.4.0.dist-info/WHEEL
test_api_sar-0.4.0.dist-info/top_level.txt
test_api_sar-0.4.0.dist-info/RECORD
