Metadata-Version: 2.1
Name: test_api_sar
Version: 0.4.0
Summary: A brief description of what your package does.
Author: Your Name
Author-email: your.email@example.com
